txdb/__init__.py
txdb/_ahub.py
txdb/record.py
txdb/txdb.py
txdb/txdbregistry.py
txdb-0.0.4.dist-info/licenses/LICENSE.txt
txdb-0.0.4.dist-info/METADATA
txdb-0.0.4.dist-info/WHEEL
txdb-0.0.4.dist-info/top_level.txt
txdb-0.0.4.dist-info/RECORD
