Metadata-Version: 2.4
Name: txdb
Version: 0.0.4
Summary: Python interface to access and manipulate genome annotations in TxDB SQLite format.
Home-page: https://github.com/biocpy/txdb
Author: Jayaram Kancherla
Author-email: jayaram.kancherla@gmail.com
License: MIT
Project-URL: Documentation, https://github.com/biocpy/txdb
Platform: any
Classifier: Development Status :: 4 - Beta
Classifier: Programming Language :: Python
Requires-Python: >=3.9
License-File: LICENSE.txt
Requires-Dist: importlib-metadata; python_version < "3.8"
Requires-Dist: genomicranges
Requires-Dist: biocframe
Requires-Dist: pybiocfilecache
Provides-Extra: testing
Requires-Dist: setuptools; extra == "testing"
Requires-Dist: pytest; extra == "testing"
Requires-Dist: pytest-cov; extra == "testing"
Dynamic: license-file
